{
  "config": {
    "dataset_name": "cora",
    "base_model": "GCN",
    "unlearning_methods": "GraphEraser",
    "unlearn_ratio": 0.05,
    "random_seed": 2024,
    "strategies_requested": [
      "random",
      "degree",
      "pagerank",
      "tracin",
      "im",
      "hybrid"
    ]
  },
  "results": [
    {
      "strategy": "random",
      "perf_before": 0.7952029520295203,
      "perf_retrain": 0.7859778597785979,
      "perf_unlearn": 0.7822878228782287,
      "drop_retrain": 0.009225092250922384,
      "gap": 0.0036900369003691758,
      "gap_pct": 0.46948356807513913,
      "mean_pred_shift": 0.20865964889526367,
      "max_pred_shift": 0.994737982749939,
      "fraction_flipped": 0.20758385956287384
    },
    {
      "strategy": "degree",
      "perf_before": 0.8007380073800738,
      "perf_retrain": 0.7749077490774909,
      "perf_unlearn": 0.7767527675276754,
      "drop_retrain": 0.025830258302582898,
      "gap": -0.0018450184501844769,
      "gap_pct": -0.2380952380952348,
      "mean_pred_shift": 0.2132873386144638,
      "max_pred_shift": 0.9983270168304443,
      "fraction_flipped": 0.20709770917892456
    },
    {
      "strategy": "pagerank",
      "perf_before": 0.8284132841328413,
      "perf_retrain": 0.8007380073800738,
      "perf_unlearn": 0.7933579335793358,
      "drop_retrain": 0.027675276752767486,
      "gap": 0.0073800738007380184,
      "gap_pct": 0.9216589861751165,
      "mean_pred_shift": 0.2275858223438263,
      "max_pred_shift": 0.9894450306892395,
      "fraction_flipped": 0.219144806265831
    },
    {
      "strategy": "tracin",
      "perf_before": 0.7767527675276754,
      "perf_retrain": 0.7527675276752768,
      "perf_unlearn": 0.7453874538745388,
      "drop_retrain": 0.023985239852398643,
      "gap": 0.0073800738007380184,
      "gap_pct": 0.9803921568627465,
      "mean_pred_shift": 0.2503925561904907,
      "max_pred_shift": 0.9936475157737732,
      "fraction_flipped": 0.252092570066452
    },
    {
      "strategy": "im",
      "perf_before": 0.7785977859778597,
      "perf_retrain": 0.8025830258302583,
      "perf_unlearn": 0.8118081180811808,
      "drop_retrain": -0.023985239852398643,
      "gap": -0.009225092250922495,
      "gap_pct": -1.14942528735632,
      "mean_pred_shift": 0.2158517986536026,
      "max_pred_shift": 0.9930026531219482,
      "fraction_flipped": 0.21368783712387085
    },
    {
      "strategy": "hybrid",
      "perf_before": 0.7970479704797048,
      "perf_retrain": 0.7693726937269372,
      "perf_unlearn": 0.8173431734317345,
      "drop_retrain": 0.027675276752767597,
      "gap": -0.047970479704797286,
      "gap_pct": -6.235011990407706,
      "mean_pred_shift": 0.22441184520721436,
      "max_pred_shift": 0.99851393699646,
      "fraction_flipped": 0.2240275740623474
    }
  ],
  "timestamp": "2026-02-22T06:33:13.055784",
  "repair_meta": {
    "repair_mode": true,
    "dry_run": false,
    "requested": 6,
    "completed_before": 0,
    "executed_now": 6,
    "missing_before": 6
  }
}