{
  "config": {
    "dataset_name": "citeseer",
    "base_model": "GIN",
    "unlearning_methods": "GIF",
    "unlearn_ratio": 0.2,
    "random_seed": 42,
    "baseline_k": 5,
    "strategies_requested": [
      "random",
      "degree",
      "pagerank",
      "tracin",
      "im_v4",
      "hybrid_v4"
    ]
  },
  "results": [
    {
      "strategy": "random",
      "baseline_f1_after": 0.7069069069069069,
      "attack_f1_after": 0.7102,
      "gap": 0.0032930930930931135,
      "relative_f1_drop": -0.0032930930930931135
    },
    {
      "strategy": "degree",
      "baseline_f1_after": 0.7069069069069069,
      "attack_f1_after": 0.7267,
      "gap": 0.019793093093093073,
      "relative_f1_drop": -0.019793093093093073
    },
    {
      "strategy": "pagerank",
      "baseline_f1_after": 0.7069069069069069,
      "attack_f1_after": 0.7297,
      "gap": 0.022793093093093075,
      "relative_f1_drop": -0.022793093093093075
    },
    {
      "strategy": "tracin",
      "baseline_f1_after": 0.7069069069069069,
      "attack_f1_after": 0.7267,
      "gap": 0.019793093093093073,
      "relative_f1_drop": -0.019793093093093073
    },
    {
      "strategy": "im_v4",
      "baseline_f1_after": 0.7069069069069069,
      "attack_f1_after": 0.7237,
      "gap": 0.01679309309309307,
      "relative_f1_drop": -0.01679309309309307
    },
    {
      "strategy": "hybrid_v4",
      "baseline_f1_after": 0.7069069069069069,
      "attack_f1_after": 0.7282,
      "gap": 0.02129309309309302,
      "relative_f1_drop": -0.02129309309309302
    }
  ],
  "timestamp": "2026-02-27T05:03:53.274635"
}