{
  "cache_key": "9354c1e94436603f",
  "cached_at": "2026-02-26T21:55:21.664195",
  "config": {
    "dataset_name": "cora",
    "base_model": "GAT",
    "unlearning_methods": "GIF",
    "unlearn_ratio": 0.1,
    "k": 270,
    "random_seed": 2024,
    "seed": 2024,
    "strategy_name": "random",
    "unlearn_task": "node",
    "downstream_task": "node",
    "is_transductive": true,
    "is_balanced": false
  },
  "result": {
    "strategy_name": "random",
    "selected_nodes": [
      1784,
      1239,
      1329,
      2571,
      2575,
      432,
      511,
      857,
      2641,
      2022,
      2662,
      617,
      2512,
      288,
      2364,
      2475,
      320,
      1183,
      874,
      2183,
      2374,
      158,
      358,
      2255,
      2553,
      2464,
      568,
      892,
      1417,
      196,
      481,
      2011,
      1502,
      2107,
      1181,
      2532,
      1017,
      2360,
      1680,
      514,
      1666,
      944,
      1913,
      2403,
      365,
      862,
      1609,
      35,
      197,
      741,
      493,
      2334,
      129,
      907,
      1777,
      513,
      2010,
      2347,
      2316,
      1221,
      932,
      29,
      1049,
      800,
      941,
      1585,
      2280,
      1915,
      1422,
      1476,
      959,
      469,
      260,
      231,
      835,
      272,
      1025,
      1817,
      1193,
      229,
      2446,
      1872,
      251,
      1559,
      700,
      2201,
      142,
      253,
      783,
      2458,
      1235,
      1312,
      1521,
      614,
      582,
      345,
      2513,
      1048,
      2633,
      2491,
      2166,
      587,
      1702,
      887,
      2669,
      366,
      2064,
      1902,
      1677,
      2339,
      2142,
      132,
      1827,
      1454,
      434,
      1152,
      179,
      161,
      1653,
      1510,
      1489,
      2587,
      776,
      2304,
      657,
      45,
      2111,
      1200,
      575,
      609,
      2236,
      206,
      1157,
      2245,
      2664,
      705,
      2303,
      2502,
      1995,
      1011,
      639,
      1565,
      1185,
      241,
      2029,
      1866,
      2227,
      442,
      1009,
      1055,
      729,
      1484,
      1716,
      973,
      731,
      2261,
      333,
      1531,
      1871,
      1897,
      2657,
      2195,
      429,
      1062,
      2379,
      1355,
      1713,
      2659,
      243,
      2441,
      1819,
      24,
      2695,
      1694,
      2563,
      2224,
      2194,
      2476,
      2467,
      2680,
      2221,
      522,
      1078,
      591,
      93,
      801,
      2704,
      334,
      1550,
      599,
      445,
      809,
      1594,
      520,
      266,
      1083,
      2044,
      230,
      1735,
      1760,
      54,
      1493,
      1686,
      215,
      2286,
      1545,
      636,
      97,
      980,
      812,
      1401,
      2049,
      2331,
      1841,
      211,
      81,
      474,
      2450,
      2074,
      2367,
      1467,
      2455,
      136,
      1836,
      654,
      352,
      530,
      1066,
      2539,
      78,
      289,
      170,
      1685,
      4,
      1886,
      538,
      1613,
      660,
      1388,
      191,
      192,
      168,
      915,
      1972,
      1752,
      2431,
      1199,
      914,
      2356,
      52,
      2567,
      937,
      1407,
      992,
      1226,
      2422,
      2340,
      848,
      878,
      2155,
      1589,
      1513,
      2388,
      2372,
      1346,
      1367,
      943,
      1470,
      140,
      2437
    ],
    "f1_before": null,
    "f1_after": 0.8339,
    "f1_drop": null,
    "f1_drop_ratio": null,
    "unlearn_time": 1.0665,
    "total_time": 2.6792,
    "selection_time": 0.0,
    "selection_reuse_time": null,
    "selection_cache_hit": false,
    "selection_cache_key": "bb1cfe668abe6ca9669f8775bb2eecc3",
    "selection_cache_source": null,
    "mia_auc": 0.579,
    "run_timestamp": "2026-02-26T21:55:21.664195",
    "config": {
      "cuda": 0,
      "num_threads": 1,
      "root_path": "./",
      "dataset_name": "cora",
      "is_transductive": true,
      "cal_mem": false,
      "is_balanced": false,
      "use_batch": false,
      "poison": true,
      "process": "",
      "noise_ratio": 0.1,
      "sparsity_ratio": 0.1,
      "base_model": "GAT",
      "unlearning_methods": "GIF",
      "train_ratio": 0.8,
      "val_ratio": 0,
      "test_ratio": 0.2,
      "exp": "sequence",
      "unlearn_trainer": "BaseTrainer",
      "parameter_task": "normal",
      "downstream_task": "node",
      "unlearn_task": "node",
      "num_epochs": 100,
      "test_freq": 10,
      "batch_size": 64,
      "opt_lr": 0.001,
      "opt_decay": 0.0001,
      "std": 0.01,
      "alpha": 0.5,
      "optimizer": "Adam",
      "lam": 0.01,
      "eps": 1.0,
      "verbose": false,
      "compare_gnorm": false,
      "num_unlearned_nodes": 270,
      "proportion_unlearned_nodes": 0.1,
      "proportion_unlearned_edges": 0.1,
      "proportion_unlearned_edges_num": 0.0001,
      "unlearn_ratio": 0.1,
      "unlearn_lr": 0.01,
      "propagation_prob": 0.1,
      "mc_rounds": 100,
      "candidate_fraction": 1.0,
      "im_v4_batch_size": 5,
      "GUIDE_methods": "SR",
      "GUIDE_repair_methods": "MixUp",
      "num_shards": 10,
      "partition_method": "lpa_base",
      "opt_num_epochs": 20,
      "ratio_deleted_edges": 0,
      "aggregator": "optimal",
      "shard_size_delta": 0.005,
      "terminate_delta": 0,
      "is_prune": false,
      "is_partition": true,
      "is_constrained": true,
      "is_train_target_model": true,
      "is_gen_embedding": true,
      "num_runs": 1,
      "num_opt_samples": 1000,
      "test_batch_size": 64,
      "use_test_neighbors": true,
      "repartition": false,
      "checkpoint_dir": "./data/GNNDelete/checkpoint_node",
      "random_seed": 2024,
      "hidden_dim": 64,
      "in_dim": 128,
      "out_dim": 64,
      "unlearning_model": "gnndelete_nodeemb",
      "df": "out",
      "df_idx": "none",
      "df_size": 0.5,
      "neg_sample_random": "non_connected",
      "loss_fct": "mse_mean",
      "loss_type": "both_layerwise",
      "train_batch": 10,
      "test_batch": 5,
      "l2": 1e-05,
      "early_stop": true,
      "patience": 5,
      "feature": false,
      "feature_update": true,
      "emb_dim": 32,
      "max_degree": false,
      "damping": 0.0,
      "approx": "cg",
      "depth": 300,
      "GIF_method": "GIF",
      "GIF_exp": "unlearning",
      "is_split": true,
      "iteration": 100,
      "scale": 1000000000,
      "damp": 0.0,
      "GNN_layer": 3,
      "unlearning_epochs": 50,
      "Budget": 0.1,
      "para1": 2.5,
      "para2": 0.01,
      "para3": 250,
      "para4": 0.1,
      "para5": 10,
      "folds": 10,
      "display_step": 10,
      "rm_disp_step": 1,
      "J": 5,
      "Q": 4,
      "L": 3,
      "remove_guo": false,
      "retrain": false,
      "GST_delta": 0.0001,
      "hop_neighbors": 20,
      "dropout_times": 2,
      "use_cross_entropy": false,
      "use_adapt_gcs": false,
      "x_iters": 3,
      "y_iters": 3,
      "require_linear_span": true,
      "regen_model": true,
      "parallel_unlearning": 1,
      "result_dir": "./result/CGU",
      "dataset": "null",
      "train_mode": "ovr",
      "train_sep": false,
      "XdegNorm": false,
      "add_self_loops": true,
      "wd": 0.0005,
      "featNorm": false,
      "GPR": false,
      "balance_train": false,
      "Y_binary": "0",
      "noise_mode": "data",
      "removal_mode": "node",
      "delta": 0.0001,
      "disp": 5,
      "fix_random_seed": false,
      "compare_retrain": false,
      "compare_guo": false,
      "kappa": 0.01,
      "alpha1": 0.8,
      "alpha2": 0.5,
      "is_use_train_batch": false,
      "is_use_test_batch": false,
      "unlearn_feature_partial_ratio": 0.5,
      "gaussian_mean": 0.0,
      "gaussian_std": 0.0,
      "l": 0.25,
      "lambda": 1.0,
      "c": 0.5,
      "M": 0.25,
      "c1": 1.0,
      "lambda_edge_unlearn": 1.0,
      "gamma_2": 1.0,
      "file_name": "unlearning_results",
      "write": true,
      "eval_on_cpu": false,
      "path": "./data/ScaleGUN",
      "del_path_suffix": "unlearning_data/",
      "analysis_path": "analysis",
      "trials": 3,
      "axis_num": 1,
      "prop_algo": "MC",
      "prop_step": 3,
      "r": 0.5,
      "decay": 0.1,
      "RW": 20,
      "rmax": 0.0,
      "ppr": false,
      "weight_mode": "test",
      "optuna": false,
      "del_postfix": "",
      "del_only": false,
      "lr": 0.005,
      "num_batch_removes": 5,
      "no_retrain": true,
      "edge_idx_start": 0,
      "num_removes": 10,
      "seed": 2024,
      "strategy_name": "random",
      "k": 270
    }
  }
}