{
  "cache_key": "a6d687aff8162abd",
  "cached_at": "2026-02-26T18:31:27.115816",
  "config": {
    "dataset_name": "citeseer",
    "base_model": "GCN",
    "unlearning_methods": "GIF",
    "unlearn_ratio": 0.2,
    "k": 665,
    "random_seed": 722,
    "seed": 722,
    "strategy_name": "tracin",
    "unlearn_task": "node",
    "downstream_task": "node",
    "is_transductive": true,
    "is_balanced": false
  },
  "result": {
    "strategy_name": "tracin",
    "selected_nodes": [
      730,
      1768,
      248,
      2136,
      2365,
      1942,
      2914,
      1306,
      1217,
      145,
      2818,
      804,
      225,
      2519,
      534,
      335,
      1665,
      138,
      1666,
      797,
      2842,
      778,
      150,
      55,
      3245,
      715,
      1177,
      661,
      2917,
      1452,
      2877,
      2360,
      3178,
      1759,
      477,
      2089,
      3308,
      980,
      1383,
      514,
      1218,
      2081,
      1518,
      823,
      2643,
      2526,
      3036,
      685,
      3264,
      2645,
      1631,
      870,
      3076,
      1591,
      2078,
      1738,
      2695,
      1347,
      1721,
      574,
      868,
      1434,
      338,
      1832,
      1833,
      1637,
      424,
      3105,
      655,
      3261,
      2909,
      2042,
      1559,
      1736,
      2500,
      2317,
      793,
      1338,
      43,
      709,
      1651,
      687,
      2218,
      324,
      1019,
      1352,
      2504,
      737,
      104,
      3325,
      132,
      1670,
      2027,
      975,
      2092,
      825,
      509,
      2274,
      2893,
      1348,
      1461,
      974,
      1969,
      1131,
      2630,
      1690,
      3083,
      1512,
      1878,
      511,
      1264,
      2739,
      948,
      2708,
      1251,
      2401,
      348,
      3031,
      293,
      2313,
      529,
      2521,
      2761,
      2075,
      416,
      1433,
      2667,
      2633,
      2314,
      2857,
      800,
      650,
      1297,
      767,
      178,
      2662,
      627,
      2176,
      1747,
      1786,
      1861,
      2001,
      654,
      1390,
      2408,
      1655,
      2051,
      1043,
      2498,
      2595,
      1026,
      1421,
      1447,
      1430,
      371,
      957,
      902,
      1201,
      2572,
      2561,
      2656,
      1685,
      2507,
      2744,
      1196,
      2832,
      1483,
      2429,
      3142,
      311,
      2345,
      2239,
      689,
      768,
      1750,
      818,
      2964,
      936,
      339,
      2445,
      1732,
      1125,
      725,
      1642,
      1584,
      3254,
      285,
      41,
      1979,
      618,
      2327,
      746,
      69,
      2168,
      673,
      2978,
      1093,
      2424,
      1464,
      2175,
      1807,
      141,
      554,
      606,
      1101,
      95,
      1796,
      2550,
      2980,
      2529,
      1774,
      792,
      370,
      267,
      1542,
      1140,
      1090,
      1733,
      551,
      796,
      996,
      2636,
      1918,
      662,
      2227,
      2554,
      2481,
      971,
      2532,
      486,
      1976,
      537,
      1749,
      1804,
      2771,
      1473,
      26,
      2270,
      705,
      3054,
      1944,
      2400,
      2769,
      3160,
      3093,
      129,
      2670,
      2776,
      53,
      907,
      640,
      2691,
      2791,
      1135,
      2093,
      3051,
      674,
      2137,
      2999,
      297,
      149,
      1262,
      239,
      237,
      236,
      2461,
      2903,
      1016,
      706,
      2315,
      988,
      695,
      1910,
      1134,
      1321,
      967,
      1491,
      1235,
      151,
      2143,
      1847,
      648,
      3132,
      2179,
      2066,
      2960,
      1720,
      1418,
      2050,
      1244,
      816,
      2423,
      577,
      2891,
      47,
      2884,
      3207,
      1686,
      214,
      1168,
      984,
      2295,
      3089,
      649,
      1162,
      515,
      308,
      2378,
      2495,
      2095,
      1415,
      427,
      1694,
      2035,
      2096,
      1872,
      880,
      2692,
      1007,
      32,
      1772,
      2222,
      2577,
      3283,
      1266,
      3175,
      644,
      312,
      521,
      423,
      542,
      1011,
      2355,
      1988,
      844,
      2312,
      2767,
      445,
      1446,
      942,
      90,
      686,
      2425,
      1702,
      24,
      243,
      2562,
      232,
      2169,
      2615,
      2828,
      2657,
      3137,
      331,
      2147,
      57,
      780,
      294,
      700,
      1935,
      2476,
      894,
      669,
      3115,
      2113,
      2598,
      2076,
      96,
      837,
      1138,
      2082,
      2499,
      216,
      1195,
      2107,
      446,
      2900,
      209,
      1182,
      1188,
      1978,
      1654,
      221,
      3050,
      634,
      33,
      2074,
      349,
      846,
      1945,
      1465,
      350,
      2466,
      2830,
      3010,
      1641,
      2013,
      1098,
      2053,
      772,
      1358,
      859,
      2800,
      65,
      1540,
      1817,
      135,
      851,
      2647,
      2971,
      2258,
      3195,
      1997,
      2570,
      2981,
      9,
      788,
      3210,
      2339,
      92,
      2347,
      1901,
      1991,
      2831,
      1308,
      478,
      651,
      2586,
      1059,
      215,
      20,
      1110,
      803,
      2921,
      931,
      2490,
      3021,
      3067,
      563,
      379,
      556,
      2493,
      281,
      646,
      766,
      1037,
      1856,
      354,
      1337,
      1458,
      2972,
      287,
      2052,
      683,
      2528,
      541,
      2328,
      501,
      418,
      581,
      1734,
      1296,
      1067,
      1128,
      808,
      2648,
      720,
      502,
      2501,
      3326,
      1652,
      158,
      2910,
      1103,
      1797,
      2710,
      3206,
      728,
      2063,
      3216,
      1305,
      1443,
      3288,
      839,
      647,
      2056,
      3243,
      702,
      1151,
      1516,
      520,
      1769,
      1950,
      274,
      3282,
      2727,
      922,
      1356,
      2740,
      2923,
      2755,
      1639,
      1722,
      2754,
      378,
      1692,
      234,
      2086,
      456,
      929,
      1231,
      1662,
      739,
      2213,
      2911,
      614,
      2100,
      2184,
      93,
      2558,
      240,
      3298,
      540,
      489,
      2186,
      1753,
      2602,
      2942,
      513,
      956,
      3277,
      781,
      2671,
      2850,
      1905,
      2747,
      3271,
      3053,
      1444,
      2587,
      1021,
      3265,
      2172,
      824,
      1216,
      398,
      2109,
      1715,
      2666,
      1388,
      1256,
      387,
      2808,
      3084,
      1925,
      1137,
      2544,
      252,
      1682,
      2492,
      2084,
      2197,
      621,
      666,
      3151,
      1556,
      432,
      2983,
      2046,
      2117,
      2892,
      1793,
      1881,
      1613,
      1951,
      320,
      3199,
      2203,
      1227,
      3049,
      330,
      977,
      2699,
      3236,
      1146,
      2724,
      1646,
      1921,
      1748,
      1548,
      1402,
      2382,
      1323,
      2278,
      3196,
      3303,
      1521,
      2533,
      372,
      3102,
      168,
      2928,
      2223,
      253,
      743,
      2616,
      583,
      1598,
      1245,
      2198,
      1055,
      2879,
      731,
      2310,
      960,
      2048,
      3103,
      1957,
      2171,
      3140,
      2948,
      46,
      517,
      3235,
      1509,
      3006,
      1482,
      1061,
      1575,
      2180,
      1159,
      1084,
      2343,
      1104,
      1224,
      249,
      601,
      3192,
      3041,
      923,
      898,
      1812,
      1897,
      1489,
      2516,
      3267,
      826,
      3317,
      2152,
      2979,
      1197,
      2970,
      711,
      2421,
      1184,
      587,
      3055,
      1693,
      1353,
      2993,
      1396,
      1937,
      507,
      2834,
      854
    ],
    "f1_before": null,
    "f1_after": 0.7072,
    "f1_drop": null,
    "f1_drop_ratio": null,
    "unlearn_time": 1.0789,
    "total_time": 30.9991,
    "selection_time": 27.8461,
    "selection_reuse_time": null,
    "selection_cache_hit": false,
    "selection_cache_key": null,
    "selection_cache_source": null,
    "mia_auc": 0.68,
    "run_timestamp": "2026-02-26T18:31:27.114798",
    "config": {
      "cuda": 0,
      "num_threads": 1,
      "root_path": "./",
      "dataset_name": "citeseer",
      "is_transductive": true,
      "cal_mem": false,
      "is_balanced": false,
      "use_batch": false,
      "poison": true,
      "process": "",
      "noise_ratio": 0.1,
      "sparsity_ratio": 0.1,
      "base_model": "GCN",
      "unlearning_methods": "GIF",
      "train_ratio": 0.8,
      "val_ratio": 0,
      "test_ratio": 0.2,
      "exp": "sequence",
      "unlearn_trainer": "GIFTrainer",
      "parameter_task": "normal",
      "downstream_task": "node",
      "unlearn_task": "node",
      "num_epochs": 100,
      "test_freq": 10,
      "batch_size": 64,
      "opt_lr": 0.001,
      "opt_decay": 0.0001,
      "std": 0.01,
      "alpha": 0.5,
      "optimizer": "Adam",
      "lam": 0.01,
      "eps": 1.0,
      "verbose": false,
      "compare_gnorm": false,
      "num_unlearned_nodes": 332,
      "proportion_unlearned_nodes": 0.1,
      "proportion_unlearned_edges": 0.1,
      "proportion_unlearned_edges_num": 0.0001,
      "unlearn_ratio": 0.2,
      "unlearn_lr": 0.01,
      "propagation_prob": 0.1,
      "mc_rounds": 100,
      "candidate_fraction": 1.0,
      "im_v4_batch_size": 5,
      "GUIDE_methods": "SR",
      "GUIDE_repair_methods": "MixUp",
      "num_shards": 10,
      "partition_method": "lpa_base",
      "opt_num_epochs": 20,
      "ratio_deleted_edges": 0,
      "aggregator": "optimal",
      "shard_size_delta": 0.005,
      "terminate_delta": 0,
      "is_prune": false,
      "is_partition": true,
      "is_constrained": true,
      "is_train_target_model": true,
      "is_gen_embedding": true,
      "num_runs": 1,
      "num_opt_samples": 1000,
      "test_batch_size": 64,
      "use_test_neighbors": true,
      "repartition": false,
      "checkpoint_dir": "./data/GNNDelete/checkpoint_node",
      "random_seed": 722,
      "hidden_dim": 64,
      "in_dim": 128,
      "out_dim": 64,
      "unlearning_model": "gnndelete_nodeemb",
      "df": "out",
      "df_idx": "none",
      "df_size": 0.5,
      "neg_sample_random": "non_connected",
      "loss_fct": "mse_mean",
      "loss_type": "both_layerwise",
      "train_batch": 10,
      "test_batch": 5,
      "l2": 1e-05,
      "early_stop": true,
      "patience": 5,
      "feature": false,
      "feature_update": true,
      "emb_dim": 32,
      "max_degree": false,
      "damping": 0.0,
      "approx": "cg",
      "depth": 300,
      "GIF_method": "GIF",
      "GIF_exp": "unlearning",
      "is_split": true,
      "iteration": 100,
      "scale": 1000000000,
      "damp": 0.0,
      "GNN_layer": 3,
      "unlearning_epochs": 50,
      "Budget": 0.1,
      "para1": 2.5,
      "para2": 0.01,
      "para3": 250,
      "para4": 0.1,
      "para5": 10,
      "folds": 10,
      "display_step": 10,
      "rm_disp_step": 1,
      "J": 5,
      "Q": 4,
      "L": 3,
      "remove_guo": false,
      "retrain": false,
      "GST_delta": 0.0001,
      "hop_neighbors": 20,
      "dropout_times": 2,
      "use_cross_entropy": false,
      "use_adapt_gcs": false,
      "x_iters": 3,
      "y_iters": 3,
      "require_linear_span": true,
      "regen_model": true,
      "parallel_unlearning": 1,
      "result_dir": "./result/CGU",
      "dataset": "null",
      "train_mode": "ovr",
      "train_sep": false,
      "XdegNorm": false,
      "add_self_loops": true,
      "wd": 0.0005,
      "featNorm": false,
      "GPR": false,
      "balance_train": false,
      "Y_binary": "0",
      "noise_mode": "data",
      "removal_mode": "node",
      "delta": 0.0001,
      "disp": 5,
      "fix_random_seed": false,
      "compare_retrain": false,
      "compare_guo": false,
      "kappa": 0.01,
      "alpha1": 0.8,
      "alpha2": 0.5,
      "is_use_train_batch": false,
      "is_use_test_batch": false,
      "unlearn_feature_partial_ratio": 0.5,
      "gaussian_mean": 0.0,
      "gaussian_std": 0.0,
      "l": 0.25,
      "lambda": 1.0,
      "c": 0.5,
      "M": 0.25,
      "c1": 1.0,
      "lambda_edge_unlearn": 1.0,
      "gamma_2": 1.0,
      "file_name": "unlearning_results",
      "write": true,
      "eval_on_cpu": false,
      "path": "./data/ScaleGUN",
      "del_path_suffix": "unlearning_data/",
      "analysis_path": "analysis",
      "trials": 3,
      "axis_num": 1,
      "prop_algo": "MC",
      "prop_step": 3,
      "r": 0.5,
      "decay": 0.1,
      "RW": 20,
      "rmax": 0.0,
      "ppr": false,
      "weight_mode": "test",
      "optuna": false,
      "del_postfix": "",
      "del_only": false,
      "lr": 0.005,
      "num_batch_removes": 5,
      "no_retrain": true,
      "edge_idx_start": 0,
      "num_removes": 10,
      "seed": 722,
      "strategy_name": "tracin",
      "k": 665
    }
  }
}