{
  "cache_key": "fdcd2e6df8d3fc91",
  "cached_at": "2026-02-27T08:46:10.569298",
  "config": {
    "dataset_name": "cora",
    "base_model": "GCN",
    "unlearning_methods": "GNNDelete",
    "unlearn_ratio": 0.2,
    "k": 541,
    "random_seed": 2024,
    "seed": 2024,
    "strategy_name": "tracin",
    "unlearn_task": "node",
    "downstream_task": "node",
    "is_transductive": true,
    "is_balanced": false
  },
  "result": {
    "strategy_name": "tracin",
    "selected_nodes": [
      1914,
      702,
      118,
      2173,
      1076,
      1973,
      31,
      663,
      596,
      2022,
      939,
      2396,
      1501,
      2174,
      504,
      724,
      600,
      1333,
      2217,
      2608,
      1396,
      1420,
      2395,
      2170,
      2480,
      772,
      69,
      551,
      1027,
      1616,
      2228,
      1464,
      993,
      2423,
      1387,
      1351,
      1421,
      404,
      1170,
      1476,
      1487,
      779,
      2112,
      1215,
      2638,
      891,
      447,
      1851,
      2157,
      41,
      2154,
      2209,
      1674,
      1975,
      85,
      1370,
      2218,
      108,
      1647,
      604,
      2467,
      539,
      465,
      54,
      93,
      548,
      950,
      1495,
      1288,
      1972,
      1359,
      1399,
      1402,
      712,
      2326,
      1592,
      921,
      2050,
      2030,
      1917,
      1623,
      306,
      181,
      2109,
      2300,
      1919,
      2159,
      1587,
      1291,
      1660,
      2397,
      1504,
      77,
      834,
      1675,
      2132,
      1620,
      1918,
      2422,
      23,
      1482,
      2158,
      1459,
      2013,
      778,
      2457,
      2110,
      831,
      414,
      850,
      1163,
      56,
      1624,
      102,
      145,
      2488,
      96,
      1800,
      109,
      2649,
      1676,
      121,
      307,
      991,
      955,
      898,
      2168,
      2096,
      342,
      99,
      2487,
      2088,
      262,
      1915,
      104,
      581,
      1776,
      2164,
      499,
      2458,
      1158,
      682,
      2598,
      1768,
      26,
      2134,
      1074,
      1797,
      2325,
      1916,
      144,
      213,
      2278,
      2324,
      968,
      876,
      1571,
      550,
      1362,
      1283,
      1367,
      1204,
      945,
      1609,
      1699,
      1836,
      122,
      864,
      2429,
      1045,
      1505,
      980,
      1009,
      127,
      329,
      1140,
      2257,
      2318,
      2402,
      476,
      225,
      2255,
      2584,
      399,
      1782,
      611,
      2690,
      1798,
      1805,
      887,
      910,
      1767,
      1783,
      2254,
      683,
      1670,
      556,
      487,
      2086,
      655,
      2026,
      1769,
      773,
      459,
      1346,
      1773,
      136,
      2622,
      2327,
      2328,
      1789,
      36,
      491,
      1640,
      384,
      87,
      139,
      660,
      1790,
      2107,
      1572,
      2093,
      303,
      1784,
      2085,
      1328,
      495,
      1854,
      2319,
      1856,
      1770,
      2106,
      1327,
      2208,
      2478,
      1834,
      1788,
      958,
      719,
      133,
      2092,
      563,
      1991,
      1180,
      1251,
      460,
      2161,
      1245,
      112,
      2210,
      1771,
      426,
      2532,
      106,
      409,
      153,
      1337,
      1772,
      1780,
      2143,
      1778,
      350,
      138,
      2082,
      656,
      1779,
      1335,
      2090,
      608,
      42,
      1490,
      236,
      2545,
      2045,
      1552,
      126,
      2087,
      542,
      2084,
      1787,
      176,
      1324,
      103,
      1560,
      1551,
      1547,
      1786,
      294,
      1564,
      308,
      302,
      1248,
      1594,
      1791,
      484,
      685,
      2145,
      1193,
      2322,
      2079,
      1845,
      1705,
      234,
      517,
      1309,
      1253,
      1184,
      134,
      474,
      1181,
      1190,
      2046,
      272,
      1043,
      925,
      2081,
      2100,
      816,
      1236,
      2479,
      1222,
      2505,
      578,
      2105,
      733,
      628,
      2591,
      516,
      755,
      1980,
      135,
      1441,
      941,
      1394,
      803,
      1375,
      2586,
      137,
      2017,
      2331,
      1690,
      483,
      645,
      120,
      2281,
      2101,
      1979,
      1669,
      454,
      668,
      1494,
      1544,
      1105,
      1998,
      2504,
      76,
      995,
      2102,
      2103,
      1338,
      1764,
      191,
      2268,
      1311,
      424,
      2510,
      1677,
      2023,
      2428,
      2485,
      903,
      266,
      1661,
      1840,
      750,
      2098,
      1029,
      2166,
      376,
      1077,
      2024,
      1578,
      241,
      2517,
      1060,
      644,
      2178,
      1879,
      913,
      1700,
      2150,
      648,
      2291,
      878,
      844,
      130,
      220,
      863,
      115,
      2644,
      1313,
      1707,
      1882,
      2272,
      265,
      2058,
      2374,
      264,
      621,
      114,
      842,
      610,
      300,
      730,
      1982,
      1404,
      393,
      388,
      161,
      2388,
      1237,
      826,
      1896,
      1167,
      989,
      573,
      1267,
      1455,
      448,
      2528,
      360,
      2497,
      1899,
      720,
      441,
      1825,
      1113,
      1897,
      709,
      840,
      2089,
      1898,
      1963,
      344,
      1974,
      2407,
      129,
      252,
      2288,
      94,
      767,
      20,
      1268,
      728,
      739,
      2356,
      701,
      1125,
      1312,
      1958,
      1892,
      1543,
      624,
      467,
      2516,
      1409,
      2227,
      1962,
      2553,
      2424,
      1553,
      2470,
      1903,
      1128,
      2275,
      1885,
      1978,
      2287,
      2211,
      2234,
      1902,
      1883,
      195,
      1246,
      935,
      822,
      1880,
      1182,
      1878,
      419,
      917,
      559,
      446,
      1911,
      107,
      1650,
      531,
      634,
      1619,
      292,
      373,
      703,
      2047,
      971,
      1183,
      371,
      117,
      259,
      2537,
      514,
      1470,
      857,
      400,
      1354,
      70,
      1368,
      1478,
      2562,
      1537,
      647,
      1904,
      2347,
      2653,
      1829,
      2363,
      661,
      1801,
      2502,
      1172,
      62,
      1828,
      1954,
      1884,
      793,
      1227,
      1025,
      1925,
      1122,
      651,
      2491,
      479
    ],
    "f1_before": 0.8838,
    "f1_after": 0.7122,
    "f1_drop": 0.1716,
    "f1_drop_ratio": 19.42,
    "unlearn_time": 0.7681,
    "total_time": 7.5803,
    "selection_time": 6.224,
    "selection_reuse_time": null,
    "selection_cache_hit": false,
    "selection_cache_key": null,
    "selection_cache_source": null,
    "mia_auc": 0.8644,
    "run_timestamp": "2026-02-27T08:46:10.569298",
    "config": {
      "cuda": 0,
      "num_threads": 1,
      "root_path": "./",
      "dataset_name": "cora",
      "is_transductive": true,
      "cal_mem": false,
      "is_balanced": false,
      "use_batch": false,
      "poison": true,
      "process": "",
      "noise_ratio": 0.1,
      "sparsity_ratio": 0.1,
      "base_model": "GCN",
      "unlearning_methods": "GNNDelete",
      "train_ratio": 0.8,
      "val_ratio": 0,
      "test_ratio": 0.2,
      "exp": "sequence",
      "unlearn_trainer": "GNNDeleteTrainer",
      "parameter_task": "normal",
      "downstream_task": "node",
      "unlearn_task": "node",
      "num_epochs": 100,
      "test_freq": 10,
      "batch_size": 64,
      "opt_lr": 0.001,
      "opt_decay": 0.0001,
      "std": 0.01,
      "alpha": 0.5,
      "optimizer": "Adam",
      "lam": 0.01,
      "eps": 1.0,
      "verbose": false,
      "compare_gnorm": false,
      "num_unlearned_nodes": 270,
      "proportion_unlearned_nodes": 0.1,
      "proportion_unlearned_edges": 0.1,
      "proportion_unlearned_edges_num": 0.0001,
      "unlearn_ratio": 0.2,
      "unlearn_lr": 0.01,
      "propagation_prob": 0.1,
      "mc_rounds": 100,
      "candidate_fraction": 1.0,
      "im_v4_batch_size": 5,
      "GUIDE_methods": "SR",
      "GUIDE_repair_methods": "MixUp",
      "num_shards": 10,
      "partition_method": "lpa_base",
      "opt_num_epochs": 20,
      "ratio_deleted_edges": 0,
      "aggregator": "optimal",
      "shard_size_delta": 0.005,
      "terminate_delta": 0,
      "is_prune": false,
      "is_partition": true,
      "is_constrained": true,
      "is_train_target_model": true,
      "is_gen_embedding": true,
      "num_runs": 1,
      "num_opt_samples": 1000,
      "test_batch_size": 64,
      "use_test_neighbors": true,
      "repartition": false,
      "checkpoint_dir": "./data/GNNDelete/checkpoint_node",
      "random_seed": 2024,
      "hidden_dim": 64,
      "in_dim": 1433,
      "out_dim": 7,
      "unlearning_model": "gnndelete_nodeemb",
      "df": "out",
      "df_idx": "none",
      "df_size": 0.5,
      "neg_sample_random": "non_connected",
      "loss_fct": "mse_mean",
      "loss_type": "both_layerwise",
      "train_batch": 10,
      "test_batch": 5,
      "l2": 1e-05,
      "early_stop": true,
      "patience": 5,
      "feature": false,
      "feature_update": true,
      "emb_dim": 32,
      "max_degree": false,
      "damping": 0.0,
      "approx": "cg",
      "depth": 300,
      "GIF_method": "GIF",
      "GIF_exp": "unlearning",
      "is_split": true,
      "iteration": 100,
      "scale": 1000000000,
      "damp": 0.0,
      "GNN_layer": 3,
      "unlearning_epochs": 50,
      "Budget": 0.1,
      "para1": 2.5,
      "para2": 0.01,
      "para3": 250,
      "para4": 0.1,
      "para5": 10,
      "folds": 10,
      "display_step": 10,
      "rm_disp_step": 1,
      "J": 5,
      "Q": 4,
      "L": 3,
      "remove_guo": false,
      "retrain": false,
      "GST_delta": 0.0001,
      "hop_neighbors": 20,
      "dropout_times": 2,
      "use_cross_entropy": false,
      "use_adapt_gcs": false,
      "x_iters": 3,
      "y_iters": 3,
      "require_linear_span": true,
      "regen_model": true,
      "parallel_unlearning": 1,
      "result_dir": "./result/CGU",
      "dataset": "null",
      "train_mode": "ovr",
      "train_sep": false,
      "XdegNorm": false,
      "add_self_loops": true,
      "wd": 0.0005,
      "featNorm": false,
      "GPR": false,
      "balance_train": false,
      "Y_binary": "0",
      "noise_mode": "data",
      "removal_mode": "node",
      "delta": 0.0001,
      "disp": 5,
      "fix_random_seed": false,
      "compare_retrain": false,
      "compare_guo": false,
      "kappa": 0.01,
      "alpha1": 0.8,
      "alpha2": 0.5,
      "is_use_train_batch": false,
      "is_use_test_batch": false,
      "unlearn_feature_partial_ratio": 0.5,
      "gaussian_mean": 0.0,
      "gaussian_std": 0.0,
      "l": 0.25,
      "lambda": 1.0,
      "c": 0.5,
      "M": 0.25,
      "c1": 1.0,
      "lambda_edge_unlearn": 1.0,
      "gamma_2": 1.0,
      "file_name": "unlearning_results",
      "write": true,
      "eval_on_cpu": false,
      "path": "./data/ScaleGUN",
      "del_path_suffix": "unlearning_data/",
      "analysis_path": "analysis",
      "trials": 3,
      "axis_num": 1,
      "prop_algo": "MC",
      "prop_step": 3,
      "r": 0.5,
      "decay": 0.1,
      "RW": 20,
      "rmax": 0.0,
      "ppr": false,
      "weight_mode": "test",
      "optuna": false,
      "del_postfix": "",
      "del_only": false,
      "lr": 0.005,
      "num_batch_removes": 5,
      "no_retrain": true,
      "edge_idx_start": 0,
      "num_removes": 10,
      "seed": 2024,
      "strategy_name": "tracin",
      "k": 541
    }
  }
}